segment_anything_fast/__init__.py
segment_anything_fast/automatic_mask_generator.py
segment_anything_fast/build_sam.py
segment_anything_fast/dynamic_quant.py
segment_anything_fast/flash_4.py
segment_anything_fast/int_mm.py
segment_anything_fast/predictor.py
segment_anything_fast/sparse.py
segment_anything_fast/tools.py
segment_anything_fast/configs/__init__.py
segment_anything_fast/configs/flash_4_configs_a100.p
segment_anything_fast/configs/int_mm_configs_a100.p
segment_anything_fast/modeling/__init__.py
segment_anything_fast/modeling/common.py
segment_anything_fast/modeling/image_encoder.py
segment_anything_fast/modeling/mask_decoder.py
segment_anything_fast/modeling/prompt_encoder.py
segment_anything_fast/modeling/sam.py
segment_anything_fast/modeling/transformer.py
segment_anything_fast/utils/__init__.py
segment_anything_fast/utils/amg.py
segment_anything_fast/utils/onnx.py
segment_anything_fast/utils/transforms.py
ptl_segment_anything_fast-0.2.dist-info/LICENSE
ptl_segment_anything_fast-0.2.dist-info/METADATA
ptl_segment_anything_fast-0.2.dist-info/WHEEL
ptl_segment_anything_fast-0.2.dist-info/top_level.txt
ptl_segment_anything_fast-0.2.dist-info/RECORD
