Metadata-Version: 2.1
Name: ptl-segment-anything-fast
Version: 0.2
Summary: A pruned, quantized, compiled, nested and batched implementation of segment-anything
Home-page: https://github.com/pytorch-labs/segment-anything-fast
Classifier: Programming Language :: Python :: 3
Classifier: License :: OSI Approved :: MIT License
Classifier: Operating System :: OS Independent
Requires-Python: >=3.8
License-File: LICENSE
Requires-Dist: torch >=2.2.0.dev20231015
Requires-Dist: torchvision >=0.17.0.dev20231015
Requires-Dist: diskcache
Requires-Dist: pycocotools
Requires-Dist: scipy
Requires-Dist: scikit-image
